groof/__init__.py
groof/api/__init__.py
groof/api/request.py
groof/base/__init__.py
groof/base/base_document.py
groof/base/base_model.py
groof/base/constants.py
groof/base/exceptions.py
groof/base/new_object.py
groof/base/tg_method.py
groof/base/tg_object.py
groof/base/user_model.py
groof/base/user_proxy_model.py
groof/context/__init__.py
groof/context/context_dict.py
groof/context/layer0.py
groof/context/layer1.py
groof/context/layer2.py
groof/context/layer3.py
groof/context/storage.py
groof/dispatcher/__init__.py
groof/dispatcher/main.py
groof/events/__init__.py
groof/events/animation.py
groof/events/base.py
groof/events/button.py
groof/events/callback_query.py
groof/events/command.py
groof/events/contact.py
groof/events/document.py
groof/events/message.py
groof/events/my_chat_member.py
groof/events/photo.py
groof/events/start.py
groof/events/text.py
groof/filters/__init__.py
groof/filters/base.py
groof/filters/button.py
groof/filters/callback_query.py
groof/filters/chat_member.py
groof/filters/chat_type.py
groof/filters/message.py
groof/filters/my_chat_member.py
groof/filters/state.py
groof/filters/user_id.py
groof/loader.py
groof/objects/__init__.py
groof/objects/new/__init__.py
groof/objects/new/callback_button.py
groof/objects/new/inline_keyboard.py
groof/objects/new/keyboard.py
groof/objects/new/translations.py
groof/objects/new/url_button.py
groof/objects/tg_methods.py
groof/objects/tg_objects.py
groof/requests/__init__.py
groof/requests/answer_callback_query.py
groof/requests/base.py
groof/requests/copy_message.py
groof/requests/delete_message.py
groof/requests/delete_my_commands.py
groof/requests/edit_message_caption.py
groof/requests/edit_message_reply_markup.py
groof/requests/edit_message_text.py
groof/requests/get_chat.py
groof/requests/get_chat_member.py
groof/requests/get_file.py
groof/requests/get_me.py
groof/requests/get_updates.py
groof/requests/send_animation.py
groof/requests/send_audio.py
groof/requests/send_chat_action.py
groof-0.1.10.dist-info/WHEEL
groof-0.1.10.dist-info/METADATA
groof-0.1.10.dist-info/RECORD
