Metadata-Version: 2.1
Name: groof
Version: 0.1.10
License: MIT
Author-email: levch <levchenko.d.a1998@gmail.com>
Requires-Python: >=3.10
Requires-Dist: envparse>=0.2.0
Requires-Dist: mongoengine>=0.24.2
Requires-Dist: pyyaml>=6.0
Requires-Dist: requests>=2.28.1
